devpi_passwd_reset/__init__.py
devpi_passwd_reset/hookspecs.py
devpi_passwd_reset/main.py
devpi_passwd_reset/views.py
devpi_passwd_reset/templates/passwd_reset.pt
devpi_passwd_reset/templates/passwd_reset_request.pt
devpi_passwd_reset-2.0.1.dist-info/LICENSE
devpi_passwd_reset-2.0.1.dist-info/METADATA
devpi_passwd_reset-2.0.1.dist-info/WHEEL
devpi_passwd_reset-2.0.1.dist-info/entry_points.txt
devpi_passwd_reset-2.0.1.dist-info/top_level.txt
devpi_passwd_reset-2.0.1.dist-info/RECORD
