Metadata-Version: 2.1
Name: devpi-passwd-reset
Version: 2.0.1
Summary: devpi-passwd-reset: password reset view for devpi-web
Home-page: https://github.com/devpi/devpi-passwd-reset
Maintainer: Florian Schulze
Maintainer-email: florian.schulze@gmx.net
License: MIT
Classifier: Environment :: Web Environment
Classifier: Intended Audience :: Developers
Classifier: Intended Audience :: System Administrators
Classifier: License :: OSI Approved :: MIT License
Classifier: Programming Language :: Python
Classifier: Programming Language :: Python :: 3
Classifier: Programming Language :: Python :: 3.7
Classifier: Programming Language :: Python :: 3.8
Classifier: Programming Language :: Python :: 3.9
Classifier: Programming Language :: Python :: 3.10
Classifier: Programming Language :: Python :: 3.11
Requires-Python: >=3.7
License-File: LICENSE
Requires-Dist: PyYAML
Requires-Dist: devpi-server>=6.0.0
Requires-Dist: devpi-web
Requires-Dist: pyramid-mailer
